[{"zoom":12,"data":{"NMG-LNG-ZD-128":{"enableScale":true,"iconSize":36.61,"fontSize":20.34,"fontVerticalOffset":-36}}},{"zoom":11.4,"data":{"NMG-LNG-GD-1912414656687079428":{"enableScale":true,"iconSize":34.78,"fontSize":19.32,"fontHorizontalOffset":-160}}},{"zoom":10.9,"data":{"NMG-LNG-ZD-135":{"enableScale":true,"iconSize":33.25,"iconHorizontalOffset":0,"fontSize":18.47,"fontHorizontalOffset":114},"NMG-LNG-ZD-12":{"enableScale":true,"iconSize":33.25,"iconVerticalOffset":0,"fontSize":18.47,"fontHorizontalOffset":-140},"NMG-LNG-GD-7":{"enableScale":true,"iconSize":33.25,"fontSize":18.47,"fontHorizontalOffset":-200}}},{"zoom":10.8,"data":{"NMG-LNG-ZD-12":{"enableScale":true,"iconSize":32.95,"iconVerticalOffset":0,"fontSize":0},"NMG-LNG-GD-1912414656494141447":{"enableScale":true,"iconSize":32.95,"iconVerticalOffset":0,"fontSize":18.31,"fontHorizontalOffset":-180},"NMG-LNG-GD-5":{"enableScale":true,"iconSize":32.95,"iconHorizontalOffset":35.59,"fontSize":18.31,"fontHorizontalOffset":199}}},{"zoom":10.6,"data":{"NMG-LNG-GD-1912414656561250312":{"enableScale":true,"iconSize":32.34,"iconVerticalOffset":0,"fontSize":17.97,"fontVerticalOffset":-30}}},{"zoom":10.5,"data":{"NMG-LNG-GD-5":{"enableScale":true,"iconSize":32.03,"iconHorizontalOffset":35.59,"fontSize":0},"NMG-LNG-GD-1912414656624164867":{"enableScale":true,"iconSize":32.03,"iconVerticalOffset":59.39,"fontSize":17.8,"fontVerticalOffset":59.39,"fontHorizontalOffset":150}}},{"zoom":10.4,"data":{"NMG-LNG-ZD-127":{"enableScale":true,"iconSize":31.73,"fontSize":17.63,"fontVerticalOffset":-29},"NMG-LNG-GD-6":{"enableScale":true,"iconSize":31.73,"iconHorizontalOffset":0,"fontSize":17.63,"fontHorizontalOffset":164}}},{"zoom":10.2,"data":{"NMG-LNG-GD-1912414656624164866":{"enableScale":true,"iconSize":31.12,"iconHorizontalOffset":-16.44,"fontSize":17.29,"fontVerticalOffset":30}}},{"zoom":10.1,"data":{"NMG-LNG-ZD-135":{"enableScale":true,"iconSize":30.81,"iconHorizontalOffset":0,"fontSize":0}}},{"zoom":10,"data":{"NMG-LNG-ZD-2":{"enableScale":true,"iconSize":30.51,"iconVerticalOffset":0,"fontSize":16.95,"fontVerticalOffset":30},"NMG-LNG-GD-1912414656561250309":{"enableScale":true,"iconSize":30.51,"iconVerticalOffset":0,"fontSize":16.95,"fontHorizontalOffset":-126},"NMG-LNG-GD-1912414656494141446":{"enableScale":true,"iconSize":30.51,"iconVerticalOffset":-39.4,"fontSize":16.95,"fontVerticalOffset":-39.4,"fontHorizontalOffset":-160},"NMG-LNG-ZD-125":{"enableScale":true,"iconSize":30.51,"fontSize":16.95,"fontHorizontalOffset":134}}},{"zoom":9.9,"data":{"NMG-LNG-GD-1912414656359923716":{"enableScale":true,"iconSize":30.2,"iconHorizontalOffset":-16.78,"iconVerticalOffset":16.78,"fontSize":16.78,"fontHorizontalOffset":-198,"fontVerticalOffset":16.78},"NMG-LNG-GD-1912414656427032579":{"enableScale":true,"iconSize":30.2,"iconVerticalOffset":33.56,"fontSize":16.78,"fontVerticalOffset":64},"NMG-LNG-ZD-102":{"enableScale":true,"iconSize":30.2,"fontSize":16.78,"fontHorizontalOffset":106},"NMG-LNG-GD-1912414656494141448":{"enableScale":true,"iconSize":30.2,"fontSize":16.78,"fontHorizontalOffset":-160}}},{"zoom":9.8,"data":{"NMG-LNG-ZD-2":{"enableScale":true,"iconSize":29.9,"iconVerticalOffset":0,"fontSize":0},"NMG-LNG-ZD-118":{"enableScale":true,"iconSize":29.9,"iconVerticalOffset":15,"fontSize":16.61,"fontVerticalOffset":15,"fontHorizontalOffset":120}}},{"zoom":9.7,"data":{"NMG-LNG-GD-1912414656624164866":{"enableScale":true,"iconSize":29.59,"iconHorizontalOffset":-16.44,"fontSize":0},"NMG-LNG-ZD-123":{"enableScale":true,"iconSize":29.59,"fontSize":16.44,"fontVerticalOffset":-28}}},{"zoom":9.6,"data":{"NMG-LNG-GD-1912414656494141448":{"enableScale":true,"iconSize":29.29,"fontSize":0}}},{"zoom":9.5,"data":{"NMG-LNG-GD-1912414656687079428":{"enableScale":true,"iconSize":28.98,"fontSize":0},"NMG-LNG-GD-1912414656292814854":{"enableScale":true,"iconSize":28.98,"fontSize":16.1,"fontHorizontalOffset":118},"NMG-LNG-GD-1912414656624164865":{"enableScale":true,"iconSize":28.98,"fontSize":16.1,"fontVerticalOffset":30},"NMG-LNG-ZD-115":{"enableScale":true,"iconSize":28.98,"fontSize":16.1,"fontHorizontalOffset":136}}},{"zoom":9.4,"data":{"NMG-LNG-GD-1912414656494141443":{"enableScale":true,"iconSize":28.68,"fontSize":15.93,"fontHorizontalOffset":-110},"NMG-LNG-GD-7":{"enableScale":true,"iconSize":28.68,"fontSize":0},"NMG-LNG-GD-1912414657869873154":{"enableScale":true,"iconSize":28.68,"iconHorizontalOffset":-31.86,"fontSize":15.93,"fontHorizontalOffset":-196},"NMG-LNG-GD-1912414656561250307":{"enableScale":true,"iconSize":28.68,"iconHorizontalOffset":23.73,"fontSize":15.93,"fontHorizontalOffset":164}}},{"zoom":9.3,"data":{"NMG-LNG-GD-1912414656687079432":{"enableScale":true,"iconSize":28.37,"iconVerticalOffset":31.53,"fontSize":15.76,"fontVerticalOffset":31.53,"fontHorizontalOffset":-170},"NMG-LNG-GD-1912414656494141444":{"enableScale":true,"iconSize":28.37,"iconHorizontalOffset":25,"fontSize":15.76,"iconVerticalOffset":10,"fontHorizontalOffset":164,"fontVerticalOffset":10},"NMG-LNG-GD-1912414656561250308":{"enableScale":true,"iconSize":28.37,"iconHorizontalOffset":-20,"fontSize":15.76,"iconVerticalOffset":-20,"fontVerticalOffset":-50,"fontHorizontalOffset":-20},"NMG-LNG-GD-1912414656687079427":{"enableScale":true,"iconSize":28.37,"fontSize":15.76,"fontVerticalOffset":30},"NMG-LNG-ZD-108":{"enableScale":true,"iconSize":28.37,"fontSize":15.76,"fontHorizontalOffset":120},"NMG-LNG-ZD-31":{"enableScale":true,"iconSize":28.37,"fontSize":15.76,"fontVerticalOffset":-30}}},{"zoom":9.2,"data":{"NMG-LNG-ZD-133":{"enableScale":true,"iconSize":28.07,"iconHorizontalOffset":0,"fontSize":15.59,"fontHorizontalOffset":-100,"iconVerticalOffset":10,"fontVerticalOffset":10},"NMG-LNG-GD-1912414656561250309":{"enableScale":true,"iconSize":28.07,"iconVerticalOffset":0,"fontSize":0}}},{"zoom":9.1,"data":{"NMG-LNG-GD-1912414656494141446":{"enableScale":true,"iconSize":27.76,"iconVerticalOffset":-35.85,"fontSize":0,"fontVerticalOffset":0},"NMG-LNG-ZD-85":{"enableScale":true,"iconSize":27.76,"iconHorizontalOffset":0,"fontSize":15.42,"fontVerticalOffset":30},"NMG-LNG-ZD-107":{"enableScale":true,"iconSize":27.76,"fontSize":15.42,"fontVerticalOffset":27},"NMG-LNG-ZD-120":{"enableScale":true,"iconSize":27.76,"fontSize":15.42,"fontHorizontalOffset":-105}}},{"zoom":9,"data":{"NMG-LNG-ZD-32":{"enableScale":true,"iconSize":27.46,"fontSize":15.25,"fontVerticalOffset":-26},"NMG-LNG-GD-1912414656624164868":{"enableScale":true,"iconSize":27.46,"fontSize":15.25,"fontVerticalOffset":28},"NMG-LNG-ZD-129":{"enableScale":true,"iconSize":27.46,"fontSize":15.25,"fontVerticalOffset":-28}}},{"zoom":8.9,"data":{"NMG-LNG-GD-1912414656292814856":{"enableScale":true,"iconSize":27.15,"iconHorizontalOffset":0,"iconVerticalOffset":22.63,"fontSize":15.08,"fontVerticalOffset":22.63,"fontHorizontalOffset":132},"NMG-LNG-ZD-102":{"enableScale":true,"iconSize":27.15,"fontSize":0},"NMG-LNG-ZD-110":{"enableScale":true,"iconSize":27.15,"fontSize":15.08,"fontHorizontalOffset":140},"NMG-LNG-ZD-111":{"enableScale":true,"iconSize":27.15,"fontSize":15.08,"fontHorizontalOffset":110}}},{"zoom":8.8,"data":{"NMG-LNG-GD-1912414656561250305":{"enableScale":true,"iconSize":26.85,"fontSize":14.92,"fontVerticalOffset":27},"NMG-LNG-GD-1912414656624164871":{"enableScale":true,"iconSize":26.85,"iconHorizontalOffset":29.83,"iconVerticalOffset":14.92,"fontSize":14.92,"fontHorizontalOffset":284,"fontVerticalOffset":14.92},"NMG-LNG-GD-1912414656292814852":{"enableScale":true,"iconSize":26.85,"iconVerticalOffset":0,"fontSize":14.92,"fontHorizontalOffset":-134}}},{"zoom":8.7,"data":{"NMG-LNG-GD-1912414656624164868":{"enableScale":true,"iconSize":26.54,"fontSize":0},"NMG-LNG-GD-1912414656561250311":{"enableScale":true,"iconSize":26.54,"fontSize":14.75,"fontHorizontalOffset":-100},"NMG-LNG-GD-3":{"enableScale":true,"iconSize":26.54,"fontSize":14.75,"fontHorizontalOffset":-116},"NMG-LNG-GD-1912414656359923718":{"enableScale":true,"iconSize":26.54,"iconHorizontalOffset":29.49,"iconVerticalOffset":29.49,"fontSize":14.75,"fontHorizontalOffset":140,"fontVerticalOffset":29.49},"NMG-LNG-GD-1912414656359923717":{"enableScale":true,"iconSize":26.54,"iconHorizontalOffset":29.49,"fontSize":14.75,"fontHorizontalOffset":157},"NMG-LNG-ZD-36":{"enableScale":true,"iconSize":26.54,"fontSize":14.75,"fontHorizontalOffset":-148},"NMG-LNG-ZD-88":{"enableScale":true,"iconSize":26.54,"fontSize":14.75,"fontHorizontalOffset":116},"NMG-LNG-ZD-99":{"enableScale":true,"iconSize":26.54,"fontSize":14.75,"fontVerticalOffset":0,"fontHorizontalOffset":110},"NMG-LNG-ZD-94":{"enableScale":true,"iconSize":26.54,"fontSize":14.75,"fontHorizontalOffset":148},"NMG-LNG-GD-1912414656359923722":{"enableScale":true,"iconSize":26.54,"fontSize":14.75,"fontHorizontalOffset":-140},"NMG-LNG-GD-1912414656561250313":{"enableScale":true,"iconSize":26.54,"iconVerticalOffset":29.49,"fontSize":14.75,"fontVerticalOffset":29.49,"fontHorizontalOffset":116},"NMG-LNG-ZD-86":{"enableScale":true,"iconSize":26.54,"fontSize":14.75,"fontVerticalOffset":0,"fontHorizontalOffset":-110},"NMG-LNG-ZD-124":{"enableScale":true,"iconSize":26.54,"fontSize":14.75,"fontHorizontalOffset":104},"NMG-LNG-GD-1912414656427032584":{"enableScale":true,"iconSize":26.54,"iconHorizontalOffset":0,"iconVerticalOffset":-29.49,"fontSize":14.75,"fontVerticalOffset":-29.49,"fontHorizontalOffset":116},"NMG-LNG-GD-1912414656359923719":{"enableScale":true,"iconSize":26.54,"fontSize":14.75,"fontHorizontalOffset":108}}},{"zoom":8.6,"data":{"NMG-LNG-GD-1912414656561250313":{"enableScale":true,"iconSize":26.24,"iconVerticalOffset":29.15,"fontSize":0},"NMG-LNG-ZD-31":{"enableScale":true,"iconSize":26.24,"fontSize":0}}},{"zoom":8.5,"data":{"NMG-LNG-GD-1912414656359923720":{"enableScale":true,"iconSize":25.93,"iconHorizontalOffset":-28.81,"fontSize":14.41,"fontHorizontalOffset":-136},"NMG-LNG-GD-1912414656561250306":{"enableScale":true,"iconSize":25.93,"iconVerticalOffset":23.39,"fontSize":14.41,"fontVerticalOffset":48.39},"NMG-LNG-ZD-18":{"enableScale":true,"iconSize":25.93,"fontSize":14.41,"fontVerticalOffset":25}}},{"zoom":8.4,"data":{"NMG-LNG-ZD-132":{"enableScale":true,"iconSize":25.63,"iconVerticalOffset":0,"fontSize":14.24,"fontHorizontalOffset":98},"NMG-LNG-ZD-131":{"enableScale":true,"iconSize":25.63,"fontSize":14.24,"fontHorizontalOffset":-110},"NMG-LNG-ZD-91":{"enableScale":true,"iconSize":25.63,"fontSize":14.24,"fontHorizontalOffset":110},"NMG-LNG-ZD-114":{"enableScale":true,"iconSize":25.63,"fontSize":14.24,"fontVerticalOffset":-25}}},{"zoom":8.3,"data":{"NMG-LNG-ZD-88":{"enableScale":true,"iconSize":25.32,"fontSize":0},"NMG-LNG-ZD-66":{"enableScale":true,"iconSize":25.32,"fontSize":14.07,"fontHorizontalOffset":80},"NMG-LNG-GD-1912414656292814855":{"enableScale":true,"iconSize":25.32,"fontSize":14.07,"fontHorizontalOffset":168},"NMG-LNG-GD-2":{"enableScale":true,"iconSize":25.32,"fontSize":14.07,"fontHorizontalOffset":-126},"NMG-LNG-ZD-139":{"enableScale":true,"iconSize":25.32,"iconVerticalOffset":0,"fontSize":14.07,"fontHorizontalOffset":-100},"NMG-LNG-ZD-138":{"enableScale":true,"iconSize":25.32,"fontSize":14.07,"fontHorizontalOffset":102},"NMG-LNG-GD-1912414656427032580":{"enableScale":true,"iconSize":25.32,"iconVerticalOffset":0,"fontSize":14.07,"fontHorizontalOffset":-120,"fontVerticalOffset":0},"NMG-LNG-ZD-134":{"enableScale":true,"iconSize":25.32,"iconVerticalOffset":-28.13,"fontSize":14.07,"fontHorizontalOffset":104,"fontVerticalOffset":-28.13},"NMG-LNG-ZD-87":{"enableScale":true,"iconSize":25.32,"fontSize":14.07,"fontVerticalOffset":-28}}},{"zoom":8.2,"data":{"NMG-LNG-GD-1912414656359923721":{"enableScale":true,"iconSize":25.02,"iconHorizontalOffset":0,"fontSize":13.9,"fontHorizontalOffset":-130}}},{"zoom":8.1,"data":{"NMG-LNG-GD-1912414656427032579":{"enableScale":true,"iconSize":24.71,"iconVerticalOffset":27.46,"fontSize":0},"NMG-LNG-GD-6":{"enableScale":true,"iconSize":24.71,"iconHorizontalOffset":0,"fontSize":0},"NMG-LNG-GD-1912414656359923719":{"enableScale":true,"iconSize":24.71,"fontSize":0}}},{"zoom":8,"data":{"NMG-LNG-ZD-131":{"enableScale":true,"iconSize":24.41,"fontSize":0}}},{"zoom":7.9,"data":{"NMG-LNG-ZD-139":{"enableScale":true,"iconSize":24.1,"iconVerticalOffset":0,"fontSize":0},"NMG-LNG-ZD-94":{"enableScale":true,"iconSize":24.1,"fontSize":0},"NMG-LNG-ZD-105":{"enableScale":true,"iconSize":24.1,"fontSize":13.39,"fontHorizontalOffset":92},"NMG-LNG-GD-1912414656624164870":{"enableScale":true,"iconSize":24.1,"fontSize":13.39,"fontVerticalOffset":-24},"NMG-LNG-GD-1912414656359923715":{"enableScale":true,"iconSize":24.1,"fontSize":13.39,"fontVerticalOffset":-25,"fontHorizontalOffset":40},"NMG-LNG-ZD-80":{"enableScale":true,"iconSize":24.1,"fontSize":13.39,"fontHorizontalOffset":90},"NMG-LNG-ZD-119":{"enableScale":true,"iconSize":24.1,"fontSize":13.39,"fontHorizontalOffset":96},"NMG-LNG-ZD-28":{"enableScale":true,"iconSize":24.1,"fontSize":13.39,"fontVerticalOffset":24},"NMG-LNG-ZD-71":{"enableScale":true,"iconSize":24.1,"fontSize":13.39,"fontVerticalOffset":-25},"NMG-LNG-ZD-75":{"enableScale":true,"iconSize":24.1,"fontSize":13.39,"fontVerticalOffset":-24}}},{"zoom":7.8,"data":{"NMG-LNG-GD-1912414656359923717":{"enableScale":true,"iconSize":23.8,"iconHorizontalOffset":26.44,"fontSize":0},"NMG-LNG-ZD-91":{"enableScale":true,"iconSize":23.8,"fontSize":0},"NMG-LNG-GD-1":{"enableScale":true,"iconSize":23.8,"iconVerticalOffset":26.44,"fontSize":13.22,"fontVerticalOffset":50.44},"NMG-LNG-ZD-15":{"enableScale":true,"iconSize":23.8,"fontSize":13.22,"fontVerticalOffset":24},"NMG-LNG-ZD-35":{"enableScale":true,"iconSize":23.8,"fontSize":13.22,"fontHorizontalOffset":90},"NMG-LNG-GD-1912414656494141442":{"enableScale":true,"iconSize":23.8,"fontSize":13.22,"fontHorizontalOffset":102},"NMG-LNG-ZD-39":{"enableScale":true,"iconSize":23.8,"iconHorizontalOffset":0,"iconVerticalOffset":39.66,"fontSize":13.22,"fontVerticalOffset":39.66,"fontHorizontalOffset":80},"NMG-LNG-GD-9":{"enableScale":true,"iconSize":23.8,"iconVerticalOffset":-26.44,"fontSize":13.22,"fontVerticalOffset":-50.44},"NMG-LNG-ZD-43":{"enableScale":true,"iconSize":23.8,"iconVerticalOffset":-13.22,"fontSize":13.22,"fontVerticalOffset":-35.22},"NMG-LNG-ZD-37":{"enableScale":true,"iconSize":23.8,"fontSize":13.22,"fontHorizontalOffset":-80},"NMG-LNG-GD-1912414656427032578":{"enableScale":true,"iconSize":23.8,"fontSize":13.22,"fontHorizontalOffset":-102},"NMG-LNG-ZD-42":{"enableScale":true,"iconSize":23.8,"fontSize":13.22,"fontVerticalOffset":-26},"NMG-LNG-ZD-101":{"enableScale":true,"iconSize":23.8,"fontSize":13.22,"fontVerticalOffset":-26},"NMG-LNG-ZD-98":{"enableScale":true,"iconSize":23.8,"fontSize":13.22,"fontVerticalOffset":25},"NMG-LNG-ZD-100":{"enableScale":true,"iconSize":23.8,"fontSize":13.22,"fontHorizontalOffset":110},"NMG-LNG-ZD-95":{"enableScale":true,"iconSize":23.8,"fontSize":13.22,"fontVerticalOffset":25},"NMG-LNG-GD-1912414656494141445":{"enableScale":true,"iconSize":23.8,"iconVerticalOffset":26.44,"fontSize":13.22,"fontVerticalOffset":26.44,"fontHorizontalOffset":-124},"NMG-LNG-ZD-137":{"enableScale":true,"iconSize":23.8,"iconVerticalOffset":-26.44,"fontSize":13.22,"fontVerticalOffset":-26.44,"fontHorizontalOffset":104},"NMG-LNG-GD-1912414656359923714":{"enableScale":true,"iconSize":23.8,"iconHorizontalOffset":-6.61,"iconVerticalOffset":6.61,"fontSize":13.22,"fontHorizontalOffset":96,"fontVerticalOffset":6.61},"NMG-LNG-GD-1912414656427032581":{"enableScale":true,"iconSize":23.8,"iconVerticalOffset":-26.44,"fontSize":13.22,"fontVerticalOffset":-26.44,"fontHorizontalOffset":-100},"NMG-LNG-GD-8":{"enableScale":true,"iconSize":23.8,"iconHorizontalOffset":26.44,"fontSize":13.22,"fontHorizontalOffset":136},"NMG-LNG-ZD-106":{"enableScale":true,"iconSize":23.8,"fontSize":13.22,"fontHorizontalOffset":110},"NMG-LNG-GD-1912414656624164869":{"enableScale":true,"iconSize":23.8,"fontSize":13.22,"fontHorizontalOffset":96},"NMG-LNG-ZD-84":{"enableScale":true,"iconSize":23.8,"fontSize":13.22,"fontVerticalOffset":-25},"NMG-LNG-ZD-122":{"enableScale":true,"iconSize":23.8,"fontSize":13.22,"fontHorizontalOffset":90},"NMG-LNG-ZD-30":{"enableScale":true,"iconSize":23.8,"fontSize":13.22,"fontVerticalOffset":-24},"NMG-LNG-ZD-34":{"enableScale":true,"iconSize":23.8,"iconHorizontalOffset":0,"fontSize":13.22,"fontHorizontalOffset":90},"NMG-LNG-ZD-82":{"enableScale":true,"iconSize":23.8,"fontSize":13.22,"fontHorizontalOffset":100},"NMG-LNG-ZD-83":{"enableScale":true,"iconSize":23.8,"fontSize":13.22,"fontHorizontalOffset":96},"NMG-LNG-ZD-90":{"enableScale":true,"iconSize":23.8,"fontSize":13.22,"fontHorizontalOffset":110},"NMG-LNG-GD-1912414656292814853":{"enableScale":true,"iconSize":23.8,"iconVerticalOffset":-26.44,"fontSize":13.22,"fontVerticalOffset":-26.44,"fontHorizontalOffset":-120},"NMG-LNG-ZD-112":{"enableScale":true,"iconSize":23.8,"fontSize":13.22,"fontHorizontalOffset":138,"iconVerticalOffset":25,"fontVerticalOffset":25}}},{"zoom":7.7,"data":{"NMG-LNG-GD-1912414656359923718":{"enableScale":true,"iconSize":23.49,"iconHorizontalOffset":26.1,"iconVerticalOffset":26.1,"fontSize":0},"NMG-LNG-ZD-123":{"enableScale":true,"iconSize":23.49,"fontSize":0},"NMG-LNG-ZD-108":{"enableScale":true,"iconSize":23.49,"fontSize":0}}},{"zoom":7.4,"data":{"NMG-LNG-GD-1912414656359923722":{"enableScale":true,"iconSize":22.58,"fontSize":0},"NMG-LNG-ZD-134":{"enableScale":true,"iconSize":22.58,"iconVerticalOffset":-25.08,"fontSize":0},"NMG-LNG-ZD-132":{"enableScale":true,"iconSize":22.58,"iconVerticalOffset":0,"fontSize":0},"NMG-LNG-ZD-99":{"enableScale":true,"iconSize":22.58,"fontSize":0},"NMG-LNG-ZD-115":{"enableScale":true,"iconSize":22.58,"fontSize":0},"NMG-LNG-ZD-22":{"enableScale":true,"iconSize":22.58,"fontSize":12.54,"fontHorizontalOffset":80},"NMG-LNG-ZD-74":{"enableScale":true,"iconSize":22.58,"fontSize":12.54,"fontVerticalOffset":-23},"NMG-LNG-ZD-65":{"enableScale":true,"iconSize":22.58,"fontSize":12.54,"fontVerticalOffset":22},"NMG-LNG-ZD-70":{"enableScale":true,"iconSize":22.58,"fontSize":12.54,"fontVerticalOffset":22},"NMG-LNG-ZD-59":{"enableScale":true,"iconSize":22.58,"fontSize":12.54,"fontVerticalOffset":22},"NMG-LNG-ZD-29":{"enableScale":true,"iconSize":22.58,"fontSize":12.54,"fontHorizontalOffset":-80}}},{"zoom":7.3,"data":{"NMG-LNG-GD-13":{"enableScale":true,"iconSize":22.27,"iconVerticalOffset":12.37,"fontSize":12.37,"fontHorizontalOffset":96,"fontVerticalOffset":12.37}}},{"zoom":7.2,"data":{"NMG-LNG-GD-1912414656427032578":{"enableScale":true,"iconSize":21.97,"fontSize":0},"NMG-LNG-ZD-18":{"enableScale":true,"iconSize":21.97,"fontSize":0},"NMG-LNG-ZD-59":{"enableScale":true,"iconSize":21.97,"fontSize":0}}},{"zoom":7,"data":{"SMTC-2-150303":{"fontVerticalOffset":10},"SMTC-2-150603":{"fontHorizontalOffset":0,"fontVerticalOffset":-5},"SMTC-2-150627":{"fontVerticalOffset":20},"SMTC-2-150203":{"fontHorizontalOffset":-30},"SMTC-2-150204":{"fontVerticalOffset":-15},"SMTC-2-150202":{"fontVerticalOffset":20},"SMTC-2-150621":{"fontVerticalOffset":20},"SMTC-2-150205":{"fontHorizontalOffset":10,"fontVerticalOffset":-5},"SMTC-2-150221":{"fontHorizontalOffset":5},"SMTC-2-150206":{"fontVerticalOffset":-10},"SMTC-2-150104":{"fontVerticalOffset":10,"fontHorizontalOffset":10},"SMTC-2-150105":{"fontHorizontalOffset":20,"fontVerticalOffset":-3},"SMTC-2-150103":{"fontHorizontalOffset":-20,"fontVerticalOffset":-3},"SMTC-2-150102":{"fontVerticalOffset":-15},"SMTC-2-150402":{"fontVerticalOffset":10},"SMTC-2-150404":{"fontVerticalOffset":-5},"SMTC-2-150724":{"fontVerticalOffset":5},"SMTC-2-152221":{"fontHorizontalOffset":-20,"fontVerticalOffset":-10},"SMTC-2-150207":{"fontVerticalOffset":5,"fontHorizontalOffset":-5},"SMTC-2-150924":{"fontHorizontalOffset":0,"fontVerticalOffset":-5},"SMTC-2-152201":{"fontVerticalOffset":5,"fontHorizontalOffset":20},"SMTC-2-152922":{"fontVerticalOffset":30},"SMTC-2-152921":{"fontVerticalOffset":30,"fontHorizontalOffset":-10},"SMTC-2-150725":{"fontHorizontalOffset":-30},"SMTC-2-150722":{"fontVerticalOffset":20},"SMTC-2-150422":{"fontVerticalOffset":-20},"SMTC-2-150423":{"fontHorizontalOffset":50},"SMTC-2-150926":{"fontVerticalOffset":-20},"NMG-LNG-GD-8":{"enableScale":true,"iconSize":21.36,"iconHorizontalOffset":23.73,"fontSize":0},"NMG-LNG-ZD-34":{"enableScale":true,"iconSize":21.36,"iconHorizontalOffset":0,"fontSize":0},"NMG-LNG-ZD-85":{"enableScale":true,"iconSize":21.36,"iconHorizontalOffset":0,"fontSize":0},"NMG-LNG-GD-1912414656561250307":{"enableScale":true,"iconSize":21.36,"iconHorizontalOffset":23.73,"fontSize":0},"NMG-LNG-ZD-136":{"enableScale":true,"iconSize":21.36,"iconHorizontalOffset":0,"fontSize":11.86,"fontHorizontalOffset":-83},"NMG-LNG-ZD-92":{"enableScale":true,"iconSize":21.36,"fontSize":11.86,"fontHorizontalOffset":-110},"NMG-LNG-ZD-93":{"enableScale":true,"iconSize":21.36,"fontSize":11.86,"fontVerticalOffset":-23},"NMG-LNG-ZD-126":{"enableScale":true,"iconSize":21.36,"fontSize":11.86,"fontVerticalOffset":-23},"NMG-LNG-ZD-40":{"enableScale":true,"iconSize":21.36,"fontSize":11.86,"fontVerticalOffset":22},"NMG-LNG-ZD-24":{"enableScale":true,"iconSize":21.36,"fontSize":11.86,"fontHorizontalOffset":-76},"NMG-LNG-GD-1912414656687079429":{"enableScale":true,"iconSize":21.36,"fontSize":11.86,"fontVerticalOffset":22},"NMG-LNG-ZD-117":{"enableScale":true,"iconSize":21.36,"fontSize":11.86,"fontVerticalOffset":-23},"NMG-LNG-GD-1912414656687079430":{"enableScale":true,"iconSize":21.36,"iconVerticalOffset":23.73,"fontSize":11.86,"fontVerticalOffset":43.73},"NMG-LNG-ZD-41":{"enableScale":true,"iconSize":21.36,"iconVerticalOffset":0,"fontSize":11.86,"fontHorizontalOffset":80},"NMG-LNG-GD-1912414656427032582":{"enableScale":true,"iconSize":21.36,"fontSize":11.86,"fontHorizontalOffset":88},"NMG-LNG-GD-1912414656427032583":{"enableScale":true,"iconSize":21.36,"fontSize":11.86,"fontHorizontalOffset":126},"NMG-LNG-ZD-81":{"enableScale":true,"iconSize":21.36,"fontSize":11.86,"fontHorizontalOffset":94},"NMG-LNG-ZD-121":{"enableScale":true,"iconSize":21.36,"fontSize":11.86,"fontHorizontalOffset":76},"NMG-LNG-ZD-25":{"enableScale":true,"iconSize":21.36,"fontSize":11.86,"fontHorizontalOffset":70},"NMG-LNG-ZD-67":{"enableScale":true,"iconSize":21.36,"fontSize":11.86,"fontVerticalOffset":-23},"NMG-LNG-ZD-63":{"enableScale":true,"iconSize":21.36,"fontSize":11.86,"fontVerticalOffset":-23},"NMG-LNG-GD-11":{"enableScale":true,"iconSize":21.36,"fontSize":11.86,"fontVerticalOffset":22},"NMG-LNG-ZD-76":{"enableScale":true,"iconSize":21.36,"fontSize":11.86,"fontHorizontalOffset":90},"NMG-LNG-ZD-17":{"enableScale":true,"iconSize":21.36,"fontSize":11.86,"fontVerticalOffset":22},"NMG-LNG-ZD-19":{"enableScale":true,"iconSize":21.36,"fontSize":11.86,"fontHorizontalOffset":-70},"NMG-LNG-ZD-72":{"enableScale":true,"iconSize":21.36,"iconVerticalOffset":23.73,"fontSize":11.86,"fontVerticalOffset":23.73,"fontHorizontalOffset":76},"NMG-LNG-ZD-45":{"enableScale":true,"iconSize":21.36,"fontSize":11.86,"fontHorizontalOffset":114},"NMG-LNG-ZD-50":{"enableScale":true,"iconSize":21.36,"fontSize":11.86,"fontHorizontalOffset":94},"NMG-LNG-GD-4":{"enableScale":true,"iconSize":21.36,"fontSize":11.86,"fontHorizontalOffset":-100},"NMG-LNG-GD-1912414656427032577":{"enableScale":true,"iconSize":21.36,"iconVerticalOffset":23.73,"fontSize":11.86,"fontVerticalOffset":23.73,"fontHorizontalOffset":-126},"NMG-LNG-ZD-4":{"enableScale":true,"iconSize":21.36,"fontSize":11.86,"fontVerticalOffset":-23},"NMG-LNG-ZD-103":{"enableScale":true,"iconSize":21.36,"fontSize":11.86,"fontHorizontalOffset":-83},"NMG-LNG-ZD-33":{"enableScale":true,"iconSize":21.36,"iconVerticalOffset":0,"fontSize":11.86,"fontHorizontalOffset":80},"NMG-LNG-ZD-53":{"enableScale":true,"iconSize":21.36,"fontSize":11.86,"fontVerticalOffset":-23}}},{"zoom":6.9,"data":{"NMG-LNG-GD-1912414656427032583":{"enableScale":true,"iconSize":21.05,"fontSize":0},"NMG-LNG-ZD-137":{"enableScale":true,"iconSize":21.05,"iconVerticalOffset":-23.39,"fontSize":0},"NMG-LNG-ZD-122":{"enableScale":true,"iconSize":21.05,"fontSize":0},"NMG-LNG-ZD-119":{"enableScale":true,"iconSize":21.05,"fontSize":0},"NMG-LNG-GD-1912414656561250306":{"enableScale":true,"iconSize":21.05,"iconVerticalOffset":23.39,"fontSize":0},"NMG-LNG-ZD-65":{"enableScale":true,"iconSize":21.05,"fontSize":0}}},{"zoom":6.8,"data":{"NMG-LNG-GD-1912414656494141442":{"enableScale":true,"iconSize":20.75,"fontSize":0},"NMG-LNG-GD-1912414656624164865":{"enableScale":true,"iconSize":20.75,"fontSize":0},"NMG-LNG-ZD-22":{"enableScale":true,"iconSize":20.75,"fontSize":0}}},{"zoom":6.7,"data":{"NMG-LNG-ZD-45":{"enableScale":true,"iconSize":20.44,"fontSize":0}}},{"zoom":6.6,"data":{"NMG-LNG-GD-1912414657869873154":{"enableScale":true,"iconSize":20.14,"iconHorizontalOffset":-22.37,"fontSize":0},"NMG-LNG-GD-1912414656292814852":{"enableScale":true,"iconSize":20.14,"iconVerticalOffset":0,"fontSize":0},"NMG-LNG-ZD-130":{"enableScale":true,"iconSize":20.14,"fontSize":11.19,"fontVerticalOffset":24},"NMG-LNG-ZD-138":{"enableScale":true,"iconSize":20.14,"fontSize":0},"NMG-LNG-ZD-127":{"enableScale":true,"iconSize":20.14,"fontSize":0},"NMG-LNG-GD-1912414656359923720":{"enableScale":true,"iconSize":20.14,"iconHorizontalOffset":-22.37,"fontSize":0},"NMG-LNG-ZD-29":{"enableScale":true,"iconSize":20.14,"fontSize":0},"NMG-LNG-ZD-72":{"enableScale":true,"iconSize":20.14,"iconVerticalOffset":22.37,"fontSize":0,"fontVerticalOffset":0}}},{"zoom":6.5,"data":{"NMG-LNG-GD-3":{"enableScale":true,"iconSize":19.83,"fontSize":0},"NMG-LNG-GD-1912414656427032581":{"enableScale":true,"iconSize":19.83,"iconVerticalOffset":-22.03,"fontSize":0},"NMG-LNG-ZD-43":{"enableScale":true,"iconSize":19.83,"iconVerticalOffset":-11.02,"fontSize":0},"NMG-LNG-ZD-82":{"enableScale":true,"iconSize":19.83,"fontSize":0},"NMG-LNG-ZD-80":{"enableScale":true,"iconSize":19.83,"fontSize":0},"NMG-LNG-ZD-111":{"enableScale":true,"iconSize":19.83,"fontSize":0},"NMG-LNG-ZD-7":{"enableScale":true,"iconSize":19.83,"fontSize":11.02,"fontVerticalOffset":-22},"NMG-LNG-ZD-16":{"enableScale":true,"iconSize":19.83,"fontSize":11.02,"fontVerticalOffset":20},"NMG-LNG-ZD-8":{"enableScale":true,"iconSize":19.83,"fontSize":11.02,"fontHorizontalOffset":76},"NMG-LNG-ZD-5":{"enableScale":true,"iconSize":19.83,"fontSize":11.02,"fontHorizontalOffset":-76},"NMG-LNG-ZD-10":{"enableScale":true,"iconSize":19.83,"fontSize":11.02,"fontHorizontalOffset":-76},"NMG-LNG-GD-1912414656561250310":{"enableScale":true,"iconSize":19.83,"fontSize":11.02,"fontVerticalOffset":20},"NMG-LNG-ZD-6":{"enableScale":true,"iconSize":19.83,"fontSize":11.02,"fontVerticalOffset":20},"NMG-LNG-ZD-11":{"enableScale":true,"iconSize":19.83,"fontSize":11.02,"fontVerticalOffset":0,"fontHorizontalOffset":-76},"NMG-LNG-ZD-96":{"enableScale":true,"iconSize":19.83,"fontSize":11.02,"fontVerticalOffset":-20},"NMG-LNG-ZD-14":{"enableScale":true,"iconSize":19.83,"fontSize":11.02,"fontHorizontalOffset":86},"NMG-LNG-ZD-13":{"enableScale":true,"iconSize":19.83,"fontSize":11.02,"fontHorizontalOffset":-94},"NMG-LNG-GD-1912414656292814851":{"enableScale":true,"iconSize":19.83,"fontSize":11.02,"fontHorizontalOffset":85},"NMG-LNG-ZD-97":{"enableScale":true,"iconSize":19.83,"fontSize":11.02,"fontVerticalOffset":-20},"NMG-LNG-ZD-104":{"enableScale":true,"iconSize":19.83,"fontSize":11.02,"fontVerticalOffset":22},"NMG-LNG-ZD-51":{"enableScale":true,"iconSize":19.83,"fontSize":11.02,"fontVerticalOffset":-22},"NMG-LNG-ZD-55":{"enableScale":true,"iconSize":19.83,"fontSize":11.02,"fontVerticalOffset":22.03,"iconVerticalOffset":22.03,"fontHorizontalOffset":-76},"NMG-LNG-ZD-38":{"enableScale":true,"iconSize":19.83,"fontSize":11.02,"fontHorizontalOffset":64},"NMG-LNG-ZD-57":{"enableScale":true,"iconSize":19.83,"fontSize":11.02,"fontHorizontalOffset":-86},"NMG-LNG-ZD-52":{"enableScale":true,"iconSize":18,"fontSize":11.02,"fontVerticalOffset":-20},"NMG-LNG-ZD-116":{"enableScale":true,"iconSize":19.83,"fontSize":11.02,"fontHorizontalOffset":76},"NMG-LNG-ZD-44":{"enableScale":true,"iconSize":19.83,"fontSize":11.02,"fontHorizontalOffset":66},"NMG-LNG-ZD-89":{"enableScale":true,"iconSize":19.83,"fontSize":11.02,"fontHorizontalOffset":74},"NMG-LNG-ZD-113":{"enableScale":true,"iconSize":19.83,"fontSize":11.02,"fontHorizontalOffset":114},"NMG-LNG-ZD-20":{"enableScale":true,"iconSize":19.83,"fontSize":11.02,"fontVerticalOffset":20},"NMG-LNG-ZD-26":{"enableScale":true,"iconSize":19.83,"fontSize":11.02,"fontVerticalOffset":-22},"NMG-LNG-ZD-58":{"enableScale":true,"iconSize":19.83,"fontSize":11.02,"fontVerticalOffset":20},"NMG-LNG-ZD-68":{"enableScale":true,"iconSize":19.83,"fontSize":11.02,"fontVerticalOffset":-22},"NMG-LNG-GD-12":{"enableScale":true,"iconSize":19.83,"fontSize":11.02,"fontHorizontalOffset":93},"NMG-LNG-GD-10":{"enableScale":true,"iconSize":19.83,"fontSize":11.02,"fontVerticalOffset":-22},"NMG-LNG-GD-14":{"enableScale":true,"iconSize":19.83,"fontSize":11.02,"fontHorizontalOffset":86},"NMG-LNG-ZD-61":{"enableScale":true,"iconSize":19.83,"fontSize":11.02,"fontVerticalOffset":-20},"NMG-LNG-ZD-62":{"enableScale":true,"iconSize":19.83,"fontSize":11.02,"fontVerticalOffset":-20},"NMG-LNG-ZD-64":{"enableScale":true,"iconSize":18,"fontSize":11.02,"fontHorizontalOffset":60},"NMG-LNG-ZD-60":{"enableScale":true,"iconSize":19.83,"fontSize":11.02,"fontVerticalOffset":22},"NMG-LNG-ZD-69":{"enableScale":true,"iconSize":19.83,"fontSize":11.02,"fontVerticalOffset":20},"NMG-LNG-ZD-56":{"enableScale":true,"iconSize":19.83,"fontSize":11.02,"fontVerticalOffset":-22},"NMG-LNG-ZD-49":{"enableScale":true,"iconSize":19.83,"fontSize":11.02,"fontVerticalOffset":20},"NMG-LNG-GD-1912414656687079426":{"enableScale":true,"iconSize":19.83,"iconVerticalOffset":0,"fontSize":11.02,"fontVerticalOffset":-22},"NMG-LNG-ZD-47":{"enableScale":true,"iconSize":19.83,"fontSize":11.02,"fontVerticalOffset":20},"NMG-LNG-ZD-46":{"enableScale":true,"iconSize":19.83,"fontSize":11.02,"fontVerticalOffset":20},"NMG-LNG-ZD-48":{"enableScale":true,"iconSize":19.83,"fontSize":11.02,"fontVerticalOffset":-22},"NMG-LNG-GD-15":{"enableScale":true,"iconSize":19.83,"fontSize":11.02,"fontVerticalOffset":20},"NMG-LNG-GD-16":{"enableScale":true,"iconSize":19.83,"fontSize":11.02,"fontVerticalOffset":20},"NMG-LNG-ZD-21":{"enableScale":true,"iconSize":19.83,"fontSize":11.02,"fontVerticalOffset":20},"NMG-LNG-ZD-23":{"enableScale":true,"iconSize":19.83,"fontSize":11.02,"fontVerticalOffset":20},"NMG-LNG-ZD-54":{"enableScale":true,"iconSize":19.83,"fontSize":11.02,"fontVerticalOffset":20},"NMG-LNG-GD-1912414656687079431":{"enableScale":true,"iconSize":19.83,"fontSize":11.02,"fontHorizontalOffset":86},"NMG-LNG-ZD-79":{"enableScale":true,"iconSize":19.83,"fontSize":11.02,"fontHorizontalOffset":70},"NMG-LNG-ZD-27":{"enableScale":true,"iconSize":19.83,"fontSize":11.02,"fontHorizontalOffset":64},"NMG-LNG-ZD-78":{"enableScale":true,"iconSize":19.83,"fontSize":11.02,"fontHorizontalOffset":60},"NMG-LNG-ZD-77":{"enableScale":true,"iconSize":19.83,"fontSize":11.02,"fontHorizontalOffset":64},"NMG-LNG-ZD-73":{"enableScale":true,"iconSize":19.83,"fontSize":11.02,"fontHorizontalOffset":64},"NMG-LNG-ZD-9":{"enableScale":true,"iconSize":19.83,"fontSize":11.02,"fontVerticalOffset":-22}}},{"zoom":6.3,"data":{"NMG-LNG-ZD-71":{"enableScale":true,"iconSize":19.22,"fontSize":0},"NMG-LNG-ZD-69":{"enableScale":true,"iconSize":19.22,"fontSize":0}}},{"zoom":6.2,"data":{"NMG-LNG-ZD-27":{"enableScale":true,"iconSize":18.92,"fontSize":0}}},{"zoom":6,"data":{"NMG-LNG-ZD-129":{"enableScale":true,"iconSize":18.31,"fontSize":0}}},{"zoom":5.9,"data":{"NMG-LNG-GD-1":{"fontSize":0,"iconSize":18,"enableScale":true,"iconVerticalOffset":20},"NMG-LNG-GD-10":{"fontSize":0,"iconSize":18,"enableScale":true},"NMG-LNG-GD-11":{"fontSize":0,"iconSize":18,"enableScale":true},"NMG-LNG-GD-12":{"fontSize":0,"iconSize":18,"enableScale":true},"NMG-LNG-GD-14":{"fontSize":0,"iconSize":18,"enableScale":true},"NMG-LNG-GD-15":{"fontSize":0,"iconSize":18,"enableScale":true},"NMG-LNG-GD-16":{"fontSize":0,"iconSize":18,"enableScale":true},"NMG-LNG-GD-1912414656292814851":{"fontSize":0,"iconSize":18,"enableScale":true},"NMG-LNG-GD-1912414656292814853":{"fontSize":0,"iconSize":18,"enableScale":true,"iconVerticalOffset":-20},"NMG-LNG-GD-1912414656292814854":{"fontSize":0,"iconSize":18,"enableScale":true},"NMG-LNG-GD-1912414656292814855":{"fontSize":0,"iconSize":18,"enableScale":true},"NMG-LNG-GD-1912414656359923714":{"fontSize":0,"iconSize":18,"enableScale":true,"iconVerticalOffset":5,"iconHorizontalOffset":-5},"NMG-LNG-GD-1912414656359923715":{"fontSize":0,"iconSize":18,"enableScale":true},"NMG-LNG-GD-1912414656427032577":{"fontSize":0,"iconSize":18,"enableScale":true,"iconVerticalOffset":20},"NMG-LNG-GD-1912414656427032580":{"fontSize":0,"iconSize":18,"enableScale":true,"iconVerticalOffset":0},"NMG-LNG-GD-1912414656427032582":{"fontSize":0,"iconSize":18,"enableScale":true},"NMG-LNG-GD-1912414656427032584":{"fontSize":0,"iconSize":18,"enableScale":true,"iconVerticalOffset":-20},"NMG-LNG-GD-1912414656494141445":{"fontSize":0,"iconSize":18,"enableScale":true,"iconVerticalOffset":20},"NMG-LNG-GD-1912414656561250310":{"fontSize":0,"iconSize":18,"enableScale":true},"NMG-LNG-GD-1912414656624164869":{"fontSize":0,"iconSize":18,"enableScale":true},"NMG-LNG-GD-1912414656624164871":{"fontSize":0,"iconSize":18,"enableScale":true,"iconHorizontalOffset":20,"iconVerticalOffset":10},"NMG-LNG-GD-1912414656624164872":{"fontSize":0,"iconSize":18,"enableScale":true},"NMG-LNG-GD-1912414656624164873":{"fontSize":0,"iconSize":18,"enableScale":true},"NMG-LNG-GD-1912414656687079426":{"fontSize":0,"iconSize":18,"enableScale":true,"iconVerticalOffset":0},"NMG-LNG-GD-1912414656687079429":{"fontSize":0,"iconSize":18,"enableScale":true},"NMG-LNG-GD-1912414656687079431":{"fontSize":0,"iconSize":18,"enableScale":true},"NMG-LNG-GD-2":{"fontSize":0,"iconSize":18,"enableScale":true},"NMG-LNG-GD-4":{"fontSize":0,"iconSize":18,"enableScale":true},"NMG-LNG-GD-9":{"fontSize":0,"iconSize":18,"enableScale":true,"iconVerticalOffset":-20},"NMG-LNG-ZD-1":{"fontSize":0,"iconSize":18,"enableScale":true},"NMG-LNG-ZD-3":{"fontSize":0,"iconSize":18,"enableScale":true},"NMG-LNG-ZD-4":{"fontSize":0,"iconSize":18,"enableScale":true},"NMG-LNG-ZD-5":{"fontSize":0,"iconSize":18,"enableScale":true},"NMG-LNG-ZD-6":{"fontSize":0,"iconSize":18,"enableScale":true},"NMG-LNG-ZD-7":{"fontSize":0,"iconSize":18,"enableScale":true},"NMG-LNG-ZD-8":{"fontSize":0,"iconSize":18,"enableScale":true},"NMG-LNG-ZD-9":{"fontSize":0,"iconSize":18,"enableScale":true},"NMG-LNG-ZD-10":{"fontSize":0,"iconSize":18,"enableScale":true},"NMG-LNG-ZD-11":{"fontSize":0,"iconSize":18,"enableScale":true},"NMG-LNG-ZD-13":{"fontSize":0,"iconSize":18,"enableScale":true},"NMG-LNG-ZD-14":{"fontSize":0,"iconSize":18,"enableScale":true},"NMG-LNG-ZD-15":{"fontSize":0,"iconSize":18,"enableScale":true},"NMG-LNG-ZD-16":{"fontSize":0,"iconSize":18,"enableScale":true},"NMG-LNG-ZD-17":{"fontSize":0,"iconSize":18,"enableScale":true},"NMG-LNG-ZD-19":{"fontSize":0,"iconSize":18,"enableScale":true},"NMG-LNG-ZD-20":{"fontSize":0,"iconSize":18,"enableScale":true},"NMG-LNG-ZD-21":{"fontSize":0,"iconSize":18,"enableScale":true},"NMG-LNG-ZD-23":{"fontSize":0,"iconSize":18,"enableScale":true},"NMG-LNG-ZD-24":{"fontSize":0,"iconSize":18,"enableScale":true},"NMG-LNG-ZD-25":{"fontSize":0,"iconSize":18,"enableScale":true},"NMG-LNG-ZD-26":{"fontSize":0,"iconSize":18,"enableScale":true},"NMG-LNG-ZD-28":{"fontSize":0,"iconSize":18,"enableScale":true},"NMG-LNG-ZD-30":{"fontSize":0,"iconSize":18,"enableScale":true},"NMG-LNG-ZD-32":{"fontSize":0,"iconSize":18,"enableScale":true},"NMG-LNG-ZD-33":{"fontSize":0,"iconSize":18,"enableScale":true,"iconVerticalOffset":0},"NMG-LNG-ZD-35":{"fontSize":0,"iconSize":18,"enableScale":true},"NMG-LNG-ZD-36":{"fontSize":0,"iconSize":18,"enableScale":true},"NMG-LNG-ZD-37":{"fontSize":0,"iconSize":18,"enableScale":true},"NMG-LNG-ZD-38":{"fontSize":0,"iconSize":18,"enableScale":true},"NMG-LNG-ZD-40":{"fontSize":0,"iconSize":18,"enableScale":true},"NMG-LNG-ZD-41":{"fontSize":0,"iconSize":18,"enableScale":true,"iconVerticalOffset":0},"NMG-LNG-ZD-42":{"fontSize":0,"iconSize":18,"enableScale":true},"NMG-LNG-ZD-44":{"fontSize":0,"iconSize":18,"enableScale":true},"NMG-LNG-ZD-46":{"fontSize":0,"iconSize":18,"enableScale":true},"NMG-LNG-ZD-47":{"fontSize":0,"iconSize":18,"enableScale":true},"NMG-LNG-ZD-48":{"fontSize":0,"iconSize":18,"enableScale":true},"NMG-LNG-ZD-49":{"fontSize":0,"iconSize":18,"enableScale":true},"NMG-LNG-ZD-50":{"fontSize":0,"iconSize":18,"enableScale":true},"NMG-LNG-ZD-51":{"fontSize":0,"iconSize":18,"enableScale":true},"NMG-LNG-ZD-52":{"fontSize":0,"iconSize":18,"enableScale":true},"NMG-LNG-ZD-53":{"fontSize":0,"iconSize":18,"enableScale":true},"NMG-LNG-ZD-54":{"fontSize":0,"iconSize":18,"enableScale":true},"NMG-LNG-ZD-55":{"fontSize":0,"iconSize":18,"enableScale":true,"iconVerticalOffset":20},"NMG-LNG-ZD-56":{"fontSize":0,"iconSize":18,"enableScale":true},"NMG-LNG-ZD-57":{"fontSize":0,"iconSize":18,"enableScale":true},"NMG-LNG-ZD-58":{"fontSize":0,"iconSize":18,"enableScale":true},"NMG-LNG-ZD-60":{"fontSize":0,"iconSize":18,"enableScale":true},"NMG-LNG-ZD-61":{"fontSize":0,"iconSize":18,"enableScale":true},"NMG-LNG-ZD-62":{"fontSize":0,"iconSize":18,"enableScale":true},"NMG-LNG-ZD-63":{"fontSize":0,"iconSize":18,"enableScale":true},"NMG-LNG-ZD-64":{"fontSize":0,"iconSize":18,"enableScale":true},"NMG-LNG-ZD-67":{"fontSize":0,"iconSize":18,"enableScale":true},"NMG-LNG-ZD-68":{"fontSize":0,"iconSize":18,"enableScale":true},"NMG-LNG-ZD-70":{"fontSize":0,"iconSize":18,"enableScale":true},"NMG-LNG-ZD-73":{"fontSize":0,"iconSize":18,"enableScale":true},"NMG-LNG-ZD-74":{"fontSize":0,"iconSize":18,"enableScale":true},"NMG-LNG-ZD-75":{"fontSize":0,"iconSize":18,"enableScale":true},"NMG-LNG-ZD-76":{"fontSize":0,"iconSize":18,"enableScale":true},"NMG-LNG-ZD-77":{"fontSize":0,"iconSize":18,"enableScale":true},"NMG-LNG-ZD-78":{"fontSize":0,"iconSize":18,"enableScale":true},"NMG-LNG-ZD-79":{"fontSize":0,"iconSize":18,"enableScale":true},"NMG-LNG-ZD-81":{"fontSize":0,"iconSize":18,"enableScale":true},"NMG-LNG-ZD-83":{"fontSize":0,"iconSize":18,"enableScale":true},"NMG-LNG-ZD-84":{"fontSize":0,"iconSize":18,"enableScale":true},"NMG-LNG-ZD-86":{"fontSize":0,"iconSize":18,"enableScale":true},"NMG-LNG-ZD-87":{"fontSize":0,"iconSize":18,"enableScale":true},"NMG-LNG-ZD-89":{"fontSize":0,"iconSize":18,"enableScale":true},"NMG-LNG-ZD-90":{"fontSize":0,"iconSize":18,"enableScale":true},"NMG-LNG-ZD-92":{"fontSize":0,"iconSize":18,"enableScale":true},"NMG-LNG-ZD-93":{"fontSize":0,"iconSize":18,"enableScale":true},"NMG-LNG-ZD-95":{"fontSize":0,"iconSize":18,"enableScale":true},"NMG-LNG-ZD-96":{"fontSize":0,"iconSize":18,"enableScale":true},"NMG-LNG-ZD-97":{"fontSize":0,"iconSize":18,"enableScale":true},"NMG-LNG-ZD-98":{"fontSize":0,"iconSize":18,"enableScale":true},"NMG-LNG-ZD-100":{"fontSize":0,"iconSize":18,"enableScale":true},"NMG-LNG-ZD-101":{"fontSize":0,"iconSize":18,"enableScale":true},"NMG-LNG-ZD-103":{"fontSize":0,"iconSize":18,"enableScale":true},"NMG-LNG-ZD-104":{"fontSize":0,"iconSize":18,"enableScale":true},"NMG-LNG-ZD-106":{"fontSize":0,"iconSize":18,"enableScale":true},"NMG-LNG-ZD-107":{"fontSize":0,"iconSize":18,"enableScale":true},"NMG-LNG-ZD-109":{"fontSize":0,"iconSize":18,"enableScale":true},"NMG-LNG-ZD-110":{"fontSize":0,"iconSize":18,"enableScale":true},"NMG-LNG-ZD-112":{"fontSize":0,"iconSize":18,"enableScale":true},"NMG-LNG-ZD-113":{"fontSize":0,"iconSize":18,"enableScale":true},"NMG-LNG-ZD-114":{"fontSize":0,"iconSize":18,"enableScale":true},"NMG-LNG-ZD-116":{"fontSize":0,"iconSize":18,"enableScale":true},"NMG-LNG-ZD-117":{"fontSize":0,"iconSize":18,"enableScale":true},"NMG-LNG-ZD-120":{"fontSize":0,"iconSize":18,"enableScale":true},"NMG-LNG-ZD-121":{"fontSize":0,"iconSize":18,"enableScale":true},"NMG-LNG-ZD-124":{"fontSize":0,"iconSize":18,"enableScale":true},"NMG-LNG-ZD-125":{"fontSize":0,"iconSize":18,"enableScale":true},"NMG-LNG-ZD-126":{"fontSize":0,"iconSize":18,"enableScale":true},"NMG-LNG-ZD-136":{"fontSize":0,"iconSize":18,"enableScale":true,"iconHorizontalOffset":0},"NMG-LNG-ZD-39":{"enableScale":true,"iconSize":18,"iconVerticalOffset":30,"fontSize":0},"NMG-LNG-GD-1912414656687079430":{"enableScale":true,"iconSize":18,"fontSize":0,"iconVerticalOffset":20}}},{"zoom":5,"data":{"SMTC-1-152900":{"fontHorizontalOffset":-20},"SMTC-1-150800":{"fontHorizontalOffset":-10},"SMTC-1-150600":{"fontVerticalOffset":10},"SMTC-1-150200":{"fontVerticalOffset":10},"SMTC-1-150900":{"fontVerticalOffset":-10},"SMTC-2-150623":{"fontHorizontalOffset":-20},"SMTC-1-150700":{"fontVerticalOffset":10},"SMTC-1-152500":{"fontHorizontalOffset":-20},"SMTC-2-152524":{"fontVerticalOffset":20,"fontHorizontalOffset":20}}}]